getfrompexels/__init__.py
getfrompexels/collection.py
getfrompexels/endpoints.py
getfrompexels/exceptions.py
getfrompexels/photo.py
getfrompexels/query_results.py
getfrompexels/session.py
getfrompexels/type_hints.py
getfrompexels/user.py
getfrompexels/verifier.py
getfrompexels/video.py
getfrompexels/video_file.py
getfrompexels/video_picture.py
getfrompexels-1.1.0.dist-info/METADATA
getfrompexels-1.1.0.dist-info/WHEEL
getfrompexels-1.1.0.dist-info/licenses/LICENCE.md
getfrompexels-1.1.0.dist-info/RECORD
