Metadata-Version: 2.1
Name: getfrompexels
Version: 1.1.0
Summary: A wrapper that allows easy interaction with the Pexels API for everyone
Project-URL: Homepage, https://github.com/R1DF/GetFromPexels
Project-URL: Bug Tracker, https://github.com/R1DF/GetFromPexels/issues
Author: R1DF
License-File: LICENCE.md
Classifier: License :: OSI Approved :: MIT License
Classifier: Operating System :: OS Independent
Classifier: Programming Language :: Python :: 3
Requires-Python: >=3.11
